[
    {
        "id": "walk-2020-01",
        "date": "Sunday 5th January",
        "type": "Walk",
        "title": "The Hemingfords",
        "length": "10.6 miles",
        "image": "agm.png",
        "leave": "The Woodman 9:15am",
        "sortDate": "2020-01-05"
    },
    {
        "id": "walk-2020-02",
        "date": "Sunday 19th January",
        "description": "Starting from a historic village the route is in easy going Lincolnshire's rolling countryside.",
        "type": "Walk",
        "title": "Castle Bytham",
        "length": "10.2 miles",
        "startFrom": "The Castle Inn, Castle Bytham",
        "mapReference": "SK 988 184",
        "map": "Explorer 248",
        "leave": "The Woodman 9:15am",
        "image": "agm.png",
        "sortDate": "2020-01-19"
    },
    {
        "id": "walk-2020-03",
        "date": "Sunday 2nd February",
        "type": "Walk",
        "title": "Ardeley",
        "length": "9.3 miles",
        "leave": "The Woodman 8:30am",
        "image": "agm.png",
        "sortDate": "2020-02-02",
        "source":{
            "name": "The Ramblers",
            "url":""
        }
    },
    {
        "id": "walk-2020-04",
        "date": "Sunday 1st March",
        "sortDate": "2020-03-01",
        "type": "Walk",
        "title": "Calver",
        "length": "10.1 miles",
        "leave": "7:45am The Woodman; 8:05am Danish Invader",
        "image": "PeakDistrict1.png",
        "source": {
            "name": "OS Maps",
            "url": "https://osmaps.ordnancesurvey.co.uk/route/2378343/Calver"
        }
    },
    {
        "id": "walk-2020-05",
        "date": "Sunday 15th March",
        "sortDate": "2020-03-15",
        "type": "Walk",
        "title": "Redmile",
        "length": "10.8 miles",
        "leave": "8:45am The Woodman; 9:05am Danish Invader",
        "image": "BelvoirCanal.png",
        "source": {
            "name": "OS Maps",
            "url": "https://osmaps.ordnancesurvey.co.uk/route/1845064/Redmile"
        }
    },
    {
        "id": "walk-2020-06",
        "date": "Sunday 29th March",
        "sortDate": "2020-03-29",
        "type": "Walk",
        "title": "Bakewell and Wye Valley",
        "length": "10.8 miles",
        "leave": "7:45am The Woodman; 8:05am Danish Invader",
        "image": "Bakewell.png",
        "source": {
            "name": "OS Maps",
            "url": "https://osmaps.ordnancesurvey.co.uk/route/2378343/Calver"
        }
    },
    {
        "id": "walk-2020-07",
        "date": "Sunday 26th April",
        "sortDate": "2020-04-26",
        "area": "Norfolk",
        "description": "A circular route exploring the Upper Bure valley and passing through Blickling Park.",
        "type": "Walk",
        "title": "Blickling Hall",
        "length": "10.6 miles",
        "walkTime": "5 hours 30 minutes",
        "ascent": "132m (434ft)",
        "startFrom": "Car park at the west end of Blickling Park near Oulton Lodge.",
        "terrain": "Fields and estate tracks; muddy if wet.",
        "mapReference": "TG 155 289",
        "w3wAddress": "lift.curly.leotard",
        "leave": "The Woodman 8:00am",
        "image": "BlicklingHall.png",
        "grading": "Standard",
        "fuelCost": "£10.00",
        "source": {
            "name": "OS Maps",
            "url": "https://osmaps.ordnancesurvey.co.uk/route/2267012/Blickling-Hall"
        }
    },
    {
        "id": "event-2020-03",
        "date": "Tuesday 7th April",
        "type": "Social",
        "title": "Annual General Meeting",
        "leave": "The Botolph Arms, 7:30pm",
        "sortDate": "2020-04-07",
        "image": "agm.png",
        "description": [
            "The Annual General Meeting of the Club will take place on Tuesday 7th April 2020 at the Botolph Arms, Oundle Road, Peterborough starting at 7: 30pm. This is an important event in the running of the Club and we hope you will make every effort to attend.",
            "<b>AGENDA</b>",
            "<ol><li>Apologies for absence</li><li>Minutes of AGM 2019</li><li>Matters arising</li><li>Chairman’s report</li><li>Treasurer’s Report</li><li>Election of Officers</li><li>Any Other Business</li></ol>",
            "Copies of the minutes of last year's meeting will be circulated prior to the meeting.",
            "If you wish to submit a motion for discussion at the AGM, then please write it down together with the names of the proposer and seconder and hand it to one of the committee.",
            "The following posts are up for re–election:",
            "<ul><li>Chairman</li><li>Secretary</li><li>Treasurer</li><li>PR Representative</li><li>Transport Co–ordinator</li><li>Route Planner</li><li>Special Events Co–ordinator</li><li>Editor</li><li>Membership Secretary</li></ul>",
            "After the formal business which should take about half an hour, we usually stay on for a chat and a drink",
            "If you are interested in taking on a role on the committee, then please talk to one of the committee. The success of the club relies on an active membership."
        ]
    },
    {
        "id": "event-2020-04",
        "date": "Friday 10th to Monday 13th April",
        "type": "Weekend",
        "title": "Easter in the Lake District",
        "sortDate": "2020-04-10",
        "image": "LakeDistrict.png",
        "rating": "Moderate",
        "description": [
            "We have booked 10 beds at the <a href=\"https://www.yha.org.uk/hostel/yha-eskdale\" target=\"_blank\">YHA Eskdale</a> which is set in 15 acres of private grounds; the hostel is on the doorstep of the highest and most challenging Lakeland peaks. The hostel is licensed and has a self-catering kitchen.",
            "We will travel up on Friday leaving at approx. 8am and travel back Monday afternoon. The cost will be £120.75 (see booking form for options) which covers accommodation on Friday, Saturday and Sunday and breakfast on Saturday, Sunday and Monday. Packed lunches are available for an extra £5.95 each. We will probably have evening meals at the Woolpack Inn which is about 500m down the road, but there is also the option of a two–course meal in the hostel for £9.95. If you wish to self–cater the cost will be £102. Mileage costs will be in the order of £35. Non–members are subject to an additional payment of £3.",
            "You need to send a completed booking form (to be found in the Newsletter) to Alan by Sunday 22nd March to book your place.",
            "Places may be limited. First come first served. If you don’t fancy the Youth Hostel why not look into booking your own accommodation locally – but book early."
        ]
    },
    {
        "id": "event-2020-05",
        "date": "Tuesday 2nd June",
        "type": "Social",
        "title": "Club Night",
        "leave": "The Botolph Arms, 7:30pm",
        "image": "Social.png",
        "sortDate": "2020-06-02",
        "description": [
            "Come along for a drink, to chat and discuss any Club business. All welcome."
        ]
    },
    {
        "id": "event-2020-06",
        "date": "Saturday 13th June",
        "type": "Social",
        "title": "Beer by Foot",
        "leave": "The Drapers Arms, 12 Noon",
        "image": "Beer.png",
        "sortDate": "2020-06-13",
        "description": [
            "This is not the Beer by–Rail, which is later in July, but this is a walk around some of the hostelries in Peterborough."
        ]
    },
    {
        "id": "event-2020-07",
        "date": "Saturday 11th July",
        "type": "Social",
        "title": "Beer by Rail",
        "leave": "Peterborough Station, 11:30am",
        "image": "Beer.png",
        "sortDate": "2020-07-11",
        "description": [
            "This event involves taking a train to Oakham for lunch and drinks at a couple of pubs (usually including the Grainstore brewery) and then returning by train to Stamford for more drinks in some of Stamford’s many hostelries. The train is then taken to return to Peterborough where what happens depends on how people feel. Usually we have an evening meal either in Stamford of back in Peterborough depending on people’s preferences. A good day if you like beer and social chit chat. There’s also some walking between the pubs.",
            "Meet at Peterborough station about 11:30 in time to buy a ticket and get on the train. The proposed programme (which might change on a whim) is:",
            "<table><tr><td width=150>11:52</td><td>Train Peterborough to Oakham</td></tr><tr><td>12:21</td><td>Arrive Oakham to eat and drink but not necessarily in that order.</td></tr><tr><td>16:44</td><td>Train Oakham to Stamford</td></tr><tr><td>16:59</td><td>Arrive Stamford for more drinks at one or two pubs.</td></tr><tr><td>21:00</td><td>Train Stamford to Peterborough</td></tr><tr><td>21:15</td><td>Arrive Peterborough for a meal (if we haven't eaten in Stamford) and a final drink in the <a href=\"http://www.oakham-ales.co.uk/brewerytap/btwelcome.asp\">Brewery Tap</a>(if it's still open) or the<a href=\"http://www.beerintheevening.com/pubs/show.shtml/48/Drapers_Arms/Peterborough\"> Draper's Arms</a> if you're still up for it.</td></tr></table>",
            "If you live in Stamford you can meet up with us either on the Oakham train or when we get back to Stamford.",
            "Please contact Alan to let him know you are coming."
        ]
    }
]